py_logto/__init__.py
py_logto/api_client.py
py_logto/api_response.py
py_logto/configuration.py
py_logto/exceptions.py
py_logto/py.typed
py_logto/rest.py
py_logto/api/__init__.py
py_logto/api/account_center_api.py
py_logto/api/applications_api.py
py_logto/api/audit_logs_api.py
py_logto/api/authn_api.py
py_logto/api/configs_api.py
py_logto/api/connector_factories_api.py
py_logto/api/connectors_api.py
py_logto/api/custom_phrases_api.py
py_logto/api/dashboard_api.py
py_logto/api/domains_api.py
py_logto/api/experience_api.py
py_logto/api/hooks_api.py
py_logto/api/interaction_api.py
py_logto/api/my_account_api.py
py_logto/api/organization_invitations_api.py
py_logto/api/organization_roles_api.py
py_logto/api/organization_scopes_api.py
py_logto/api/organizations_api.py
py_logto/api/resources_api.py
py_logto/api/roles_api.py
py_logto/api/sign_in_experience_api.py
py_logto/api/sso_connector_providers_api.py
py_logto/api/sso_connectors_api.py
py_logto/api/status_api.py
py_logto/api/subject_tokens_api.py
py_logto/api/swagger_json_api.py
py_logto/api/systems_api.py
py_logto/api/user_assets_api.py
py_logto/api/users_api.py
py_logto/api/verification_codes_api.py
py_logto/api/verifications_api.py
py_logto/api/well_known_api.py
py_logto/models/__init__.py
py_logto/models/add_organization_applications_request.py
py_logto/models/add_organization_users_request.py
py_logto/models/add_user_identities_request.py
py_logto/models/add_user_profile_request.py
py_logto/models/add_user_profile_request_one_of.py
py_logto/models/add_user_profile_request_one_of1.py
py_logto/models/add_user_profile_request_one_of2.py
py_logto/models/add_user_profile_request_one_of3.py
py_logto/models/add_user_profile_request_one_of4.py
py_logto/models/api_interaction_bind_mfa_post_request.py
py_logto/models/api_interaction_bind_mfa_post_request_one_of.py
py_logto/models/api_interaction_bind_mfa_post_request_one_of1.py
py_logto/models/api_interaction_bind_mfa_post_request_one_of2.py
py_logto-2.0.0.dist-info/METADATA
py_logto-2.0.0.dist-info/WHEEL
py_logto-2.0.0.dist-info/top_level.txt
py_logto-2.0.0.dist-info/RECORD
