Metadata-Version: 2.1
Name: py-logto
Version: 2.0.0
Summary: Python SDK for Logto API
Home-page: https://github.com/Housain-maina/py-logto
Author: Hussaini Usman
Author-email: hussainmaina27@gmail.com
License: UNKNOWN
Keywords: OpenAPI,OpenAPI-Generator,Python SDK for Logto API
Platform: UNKNOWN
Requires-Dist: urllib3<3.0.0,>=1.25.3
Requires-Dist: python-dateutil>=2.8.2
Requires-Dist: pydantic>=2
Requires-Dist: typing-extensions>=4.7.1
